{"segmented": 0, "object": [{"name": "bus", "pose": "Unspecified", "truncated": 0, "difficult": 0, "bndbox": {"xmin": 960, "ymin": 335, "xmax": 1338, "ymax": 723}}, {"name": "rickshaw", "pose": "Unspecified", "truncated": 0, "difficult": 0, "bndbox": {"xmin": 499, "ymin": 438, "xmax": 916, "ymax": 844}}, {"name": "bike/scooter", "pose": "Unspecified", "truncated": 1, "difficult": 0, "bndbox": {"xmin": 1782, "ymin": 759, "xmax": 1920, "ymax": 1013}}, {"name": "pedestrian", "pose": "Unspecified", "truncated": 0, "difficult": 0, "bndbox": {"xmin": 356, "ymin": 440, "xmax": 497, "ymax": 755}}, {"name": "pedestrian", "pose": "Unspecified", "truncated": 0, "difficult": 0, "bndbox": {"xmin": 199, "ymin": 414, "xmax": 280, "ymax": 661}}, {"name": "pedestrian", "pose": "Unspecified", "truncated": 0, "difficult": 0, "bndbox": {"xmin": 104, "ymin": 404, "xmax": 167, "ymax": 667}}, {"name": "pedestrian", "pose": "Unspecified", "truncated": 0, "difficult": 0, "bndbox": {"xmin": 19, "ymin": 383, "xmax": 106, "ymax": 696}}], "size": {"width": 1920, "height": 1080, "depth": 3}}