{"segmented": 0, "object": [{"name": "rickshaw", "pose": "Unspecified", "truncated": 1, "difficult": 0, "bndbox": {"xmin": 4, "ymin": 198, "xmax": 627, "ymax": 1080}}, {"name": "rickshaw", "pose": "Unspecified", "truncated": 0, "difficult": 0, "bndbox": {"xmin": 712, "ymin": 457, "xmax": 1018, "ymax": 831}}, {"name": "rickshaw", "pose": "Unspecified", "truncated": 0, "difficult": 0, "bndbox": {"xmin": 1057, "ymin": 466, "xmax": 1298, "ymax": 825}}, {"name": "car", "pose": "Unspecified", "truncated": 0, "difficult": 0, "bndbox": {"xmin": 1295, "ymin": 507, "xmax": 1410, "ymax": 713}}, {"name": "bike/scooter", "pose": "Unspecified", "truncated": 0, "difficult": 0, "bndbox": {"xmin": 1436, "ymin": 519, "xmax": 1568, "ymax": 825}}, {"name": "rickshaw", "pose": "Unspecified", "truncated": 0, "difficult": 0, "bndbox": {"xmin": 642, "ymin": 428, "xmax": 760, "ymax": 704}}], "size": {"width": 1920, "height": 1080, "depth": 3}}