{"segmented": 0, "object": [{"name": "car", "pose": "Unspecified", "truncated": 0, "difficult": 0, "bndbox": {"xmin": 33, "ymin": 401, "xmax": 598, "ymax": 822}}, {"name": "car", "pose": "Unspecified", "truncated": 0, "difficult": 0, "bndbox": {"xmin": 568, "ymin": 437, "xmax": 836, "ymax": 645}}, {"name": "car", "pose": "Unspecified", "truncated": 0, "difficult": 0, "bndbox": {"xmin": 798, "ymin": 495, "xmax": 918, "ymax": 595}}, {"name": "car", "pose": "Unspecified", "truncated": 0, "difficult": 0, "bndbox": {"xmin": 960, "ymin": 481, "xmax": 1118, "ymax": 610}}, {"name": "car", "pose": "Unspecified", "truncated": 0, "difficult": 0, "bndbox": {"xmin": 1348, "ymin": 542, "xmax": 1477, "ymax": 690}}, {"name": "car", "pose": "Unspecified", "truncated": 0, "difficult": 0, "bndbox": {"xmin": 1471, "ymin": 548, "xmax": 1736, "ymax": 722}}, {"name": "pedestrian", "pose": "Unspecified", "truncated": 0, "difficult": 0, "bndbox": {"xmin": 1290, "ymin": 552, "xmax": 1343, "ymax": 638}}], "size": {"width": 1920, "height": 1080, "depth": 3}}