{"segmented": 0, "object": [{"name": "bike/scooter", "pose": "Unspecified", "truncated": 0, "difficult": 0, "bndbox": {"xmin": 589, "ymin": 440, "xmax": 862, "ymax": 781}}, {"name": "bus", "pose": "Unspecified", "truncated": 0, "difficult": 0, "bndbox": {"xmin": 562, "ymin": 378, "xmax": 851, "ymax": 569}}, {"name": "bus", "pose": "Unspecified", "truncated": 0, "difficult": 0, "bndbox": {"xmin": 895, "ymin": 445, "xmax": 1033, "ymax": 554}}, {"name": "car", "pose": "Unspecified", "truncated": 0, "difficult": 0, "bndbox": {"xmin": 1439, "ymin": 525, "xmax": 1810, "ymax": 795}}, {"name": "car", "pose": "Unspecified", "truncated": 0, "difficult": 0, "bndbox": {"xmin": 1233, "ymin": 537, "xmax": 1398, "ymax": 669}}], "size": {"width": 1920, "height": 1080, "depth": 3}}