{"segmented": 0, "object": [{"name": "rickshaw", "pose": "Unspecified", "truncated": 1, "difficult": 0, "bndbox": {"xmin": 4, "ymin": 263, "xmax": 393, "ymax": 1080}}, {"name": "car", "pose": "Unspecified", "truncated": 0, "difficult": 0, "bndbox": {"xmin": 1371, "ymin": 530, "xmax": 1568, "ymax": 672}}, {"name": "truck", "pose": "Unspecified", "truncated": 1, "difficult": 0, "bndbox": {"xmin": 1475, "ymin": 237, "xmax": 1920, "ymax": 1015}}, {"name": "pedestrian", "pose": "Unspecified", "truncated": 0, "difficult": 0, "bndbox": {"xmin": 722, "ymin": 472, "xmax": 841, "ymax": 605}}, {"name": "rickshaw", "pose": "Unspecified", "truncated": 0, "difficult": 0, "bndbox": {"xmin": 579, "ymin": 461, "xmax": 681, "ymax": 569}}], "size": {"width": 1920, "height": 1080, "depth": 3}}