{"segmented": 0, "object": [{"name": "bus", "pose": "Unspecified", "truncated": 0, "difficult": 0, "bndbox": {"xmin": 490, "ymin": 4, "xmax": 1049, "ymax": 748}}, {"name": "rickshaw", "pose": "Unspecified", "truncated": 0, "difficult": 0, "bndbox": {"xmin": 196, "ymin": 430, "xmax": 481, "ymax": 739}}, {"name": "car", "pose": "Unspecified", "truncated": 0, "difficult": 0, "bndbox": {"xmin": 1087, "ymin": 524, "xmax": 1308, "ymax": 701}}, {"name": "bike/scooter", "pose": "Unspecified", "truncated": 0, "difficult": 0, "bndbox": {"xmin": 1228, "ymin": 548, "xmax": 1572, "ymax": 933}}], "size": {"width": 1920, "height": 1080, "depth": 3}}