{"segmented": 0, "object": [{"name": "pedestrian", "pose": "Unspecified", "truncated": 0, "difficult": 0, "bndbox": {"xmin": 561, "ymin": 433, "xmax": 646, "ymax": 672}}, {"name": "pedestrian", "pose": "Unspecified", "truncated": 0, "difficult": 0, "bndbox": {"xmin": 816, "ymin": 457, "xmax": 1063, "ymax": 895}}, {"name": "pedestrian", "pose": "Unspecified", "truncated": 0, "difficult": 0, "bndbox": {"xmin": 1693, "ymin": 545, "xmax": 1887, "ymax": 919}}, {"name": "car", "pose": "Unspecified", "truncated": 0, "difficult": 0, "bndbox": {"xmin": 1234, "ymin": 530, "xmax": 1666, "ymax": 742}}, {"name": "car", "pose": "Unspecified", "truncated": 0, "difficult": 0, "bndbox": {"xmin": 863, "ymin": 492, "xmax": 1202, "ymax": 624}}, {"name": "pedestrian", "pose": "Unspecified", "truncated": 0, "difficult": 0, "bndbox": {"xmin": 402, "ymin": 389, "xmax": 469, "ymax": 557}}], "size": {"width": 1920, "height": 1080, "depth": 3}}