<annotation>
	<folder>Large 2_Nikita</folder>
	<filename>ILK7A7K3KVGQJEV.png</filename>
	<path>C:\Users\nikita\Desktop\Large 2_Nikita\ILK7A7K3KVGQJEV.png</path>
	<source>
		<database>Unknown</database>
	</source>
	<size>
		<width>1920</width>
		<height>1080</height>
		<depth>3</depth>
	</size>
	<segmented>0</segmented>
	<object>
		<name>pedestrian</name>
		<pose>Unspecified</pose>
		<truncated>0</truncated>
		<difficult>0</difficult>
		<bndbox>
			<xmin>1083</xmin>
			<ymin>546</ymin>
			<xmax>1198</xmax>
			<ymax>769</ymax>
		</bndbox>
	</object>
	<object>
		<name>car</name>
		<pose>Unspecified</pose>
		<truncated>0</truncated>
		<difficult>0</difficult>
		<bndbox>
			<xmin>752</xmin>
			<ymin>512</ymin>
			<xmax>910</xmax>
			<ymax>634</ymax>
		</bndbox>
	</object>
	<object>
		<name>bike/scooter</name>
		<pose>Unspecified</pose>
		<truncated>0</truncated>
		<difficult>0</difficult>
		<bndbox>
			<xmin>561</xmin>
			<ymin>476</ymin>
			<xmax>652</xmax>
			<ymax>643</ymax>
		</bndbox>
	</object>
	<object>
		<name>bike/scooter</name>
		<pose>Unspecified</pose>
		<truncated>0</truncated>
		<difficult>0</difficult>
		<bndbox>
			<xmin>504</xmin>
			<ymin>472</ymin>
			<xmax>571</xmax>
			<ymax>573</ymax>
		</bndbox>
	</object>
	<object>
		<name>bike/scooter</name>
		<pose>Unspecified</pose>
		<truncated>0</truncated>
		<difficult>0</difficult>
		<bndbox>
			<xmin>352</xmin>
			<ymin>446</ymin>
			<xmax>484</xmax>
			<ymax>570</ymax>
		</bndbox>
	</object>
	<object>
		<name>bike/scooter</name>
		<pose>Unspecified</pose>
		<truncated>1</truncated>
		<difficult>0</difficult>
		<bndbox>
			<xmin>1</xmin>
			<ymin>412</ymin>
			<xmax>100</xmax>
			<ymax>555</ymax>
		</bndbox>
	</object>
</annotation>
