<annotation>
	<folder>sonali</folder>
	<filename>LUMGROHFH9NRKA3.png</filename>
	<path>E:\17feb work\sonali\LUMGROHFH9NRKA3.png</path>
	<source>
		<database>Unknown</database>
	</source>
	<size>
		<width>1920</width>
		<height>1080</height>
		<depth>3</depth>
	</size>
	<segmented>0</segmented>
	<object>
		<name>car</name>
		<pose>Unspecified</pose>
		<truncated>0</truncated>
		<difficult>0</difficult>
		<bndbox>
			<xmin>758</xmin>
			<ymin>516</ymin>
			<xmax>916</xmax>
			<ymax>630</ymax>
		</bndbox>
	</object>
	<object>
		<name>pedestrian</name>
		<pose>Unspecified</pose>
		<truncated>0</truncated>
		<difficult>0</difficult>
		<bndbox>
			<xmin>219</xmin>
			<ymin>433</ymin>
			<xmax>369</xmax>
			<ymax>722</ymax>
		</bndbox>
	</object>
	<object>
		<name>pedestrian</name>
		<pose>Unspecified</pose>
		<truncated>0</truncated>
		<difficult>0</difficult>
		<bndbox>
			<xmin>1008</xmin>
			<ymin>524</ymin>
			<xmax>1055</xmax>
			<ymax>654</ymax>
		</bndbox>
	</object>
	<object>
		<name>bike/scooter</name>
		<pose>Unspecified</pose>
		<truncated>0</truncated>
		<difficult>0</difficult>
		<bndbox>
			<xmin>363</xmin>
			<ymin>451</ymin>
			<xmax>428</xmax>
			<ymax>577</ymax>
		</bndbox>
	</object>
	<object>
		<name>bike/scooter</name>
		<pose>Unspecified</pose>
		<truncated>0</truncated>
		<difficult>0</difficult>
		<bndbox>
			<xmin>475</xmin>
			<ymin>469</ymin>
			<xmax>540</xmax>
			<ymax>548</ymax>
		</bndbox>
	</object>
</annotation>
