<annotation>
	<folder>sonali</folder>
	<filename>UI2TJO002OBR3GG.png</filename>
	<path>E:\17feb work\sonali\UI2TJO002OBR3GG.png</path>
	<source>
		<database>Unknown</database>
	</source>
	<size>
		<width>1920</width>
		<height>1080</height>
		<depth>3</depth>
	</size>
	<segmented>0</segmented>
	<object>
		<name>car</name>
		<pose>Unspecified</pose>
		<truncated>0</truncated>
		<difficult>0</difficult>
		<bndbox>
			<xmin>1146</xmin>
			<ymin>539</ymin>
			<xmax>1346</xmax>
			<ymax>713</ymax>
		</bndbox>
	</object>
	<object>
		<name>car</name>
		<pose>Unspecified</pose>
		<truncated>0</truncated>
		<difficult>0</difficult>
		<bndbox>
			<xmin>1358</xmin>
			<ymin>513</ymin>
			<xmax>1419</xmax>
			<ymax>580</ymax>
		</bndbox>
	</object>
	<object>
		<name>car</name>
		<pose>Unspecified</pose>
		<truncated>0</truncated>
		<difficult>0</difficult>
		<bndbox>
			<xmin>1461</xmin>
			<ymin>516</ymin>
			<xmax>1505</xmax>
			<ymax>557</ymax>
		</bndbox>
	</object>
	<object>
		<name>pedestrian</name>
		<pose>Unspecified</pose>
		<truncated>0</truncated>
		<difficult>0</difficult>
		<bndbox>
			<xmin>972</xmin>
			<ymin>504</ymin>
			<xmax>1019</xmax>
			<ymax>595</ymax>
		</bndbox>
	</object>
</annotation>
