<annotation>
	<folder>sonali</folder>
	<filename>ZS2C5ALN6H56JSX.png</filename>
	<path>E:\17feb work\sonali\ZS2C5ALN6H56JSX.png</path>
	<source>
		<database>Unknown</database>
	</source>
	<size>
		<width>1920</width>
		<height>1080</height>
		<depth>3</depth>
	</size>
	<segmented>0</segmented>
	<object>
		<name>car</name>
		<pose>Unspecified</pose>
		<truncated>0</truncated>
		<difficult>0</difficult>
		<bndbox>
			<xmin>581</xmin>
			<ymin>413</ymin>
			<xmax>840</xmax>
			<ymax>719</ymax>
		</bndbox>
	</object>
	<object>
		<name>car</name>
		<pose>Unspecified</pose>
		<truncated>0</truncated>
		<difficult>0</difficult>
		<bndbox>
			<xmin>1028</xmin>
			<ymin>542</ymin>
			<xmax>1258</xmax>
			<ymax>695</ymax>
		</bndbox>
	</object>
	<object>
		<name>rickshaw</name>
		<pose>Unspecified</pose>
		<truncated>0</truncated>
		<difficult>0</difficult>
		<bndbox>
			<xmin>905</xmin>
			<ymin>507</ymin>
			<xmax>996</xmax>
			<ymax>613</ymax>
		</bndbox>
	</object>
</annotation>
