<annotation verified="yes">
	<folder>large</folder>
	<filename>ZXRTF57DHJR5IV2.png</filename>
	<path>C:\Users\sonali.NEWOXY\Desktop\large-20180217T072723Z-001\large\ZXRTF57DHJR5IV2.png</path>
	<source>
		<database>Unknown</database>
	</source>
	<size>
		<width>1920</width>
		<height>1080</height>
		<depth>3</depth>
	</size>
	<segmented>0</segmented>
	<object>
		<name>rickshaw</name>
		<pose>Unspecified</pose>
		<truncated>1</truncated>
		<difficult>0</difficult>
		<bndbox>
			<xmin>26</xmin>
			<ymin>222</ymin>
			<xmax>630</xmax>
			<ymax>1080</ymax>
		</bndbox>
	</object>
	<object>
		<name>rickshaw</name>
		<pose>Unspecified</pose>
		<truncated>0</truncated>
		<difficult>0</difficult>
		<bndbox>
			<xmin>699</xmin>
			<ymin>457</ymin>
			<xmax>993</xmax>
			<ymax>827</ymax>
		</bndbox>
	</object>
	<object>
		<name>rickshaw</name>
		<pose>Unspecified</pose>
		<truncated>0</truncated>
		<difficult>0</difficult>
		<bndbox>
			<xmin>1061</xmin>
			<ymin>480</ymin>
			<xmax>1284</xmax>
			<ymax>792</ymax>
		</bndbox>
	</object>
	<object>
		<name>car</name>
		<pose>Unspecified</pose>
		<truncated>0</truncated>
		<difficult>0</difficult>
		<bndbox>
			<xmin>1284</xmin>
			<ymin>530</ymin>
			<xmax>1408</xmax>
			<ymax>713</ymax>
		</bndbox>
	</object>
	<object>
		<name>bike/scooter</name>
		<pose>Unspecified</pose>
		<truncated>0</truncated>
		<difficult>0</difficult>
		<bndbox>
			<xmin>1422</xmin>
			<ymin>542</ymin>
			<xmax>1555</xmax>
			<ymax>857</ymax>
		</bndbox>
	</object>
	<object>
		<name>rickshaw</name>
		<pose>Unspecified</pose>
		<truncated>0</truncated>
		<difficult>0</difficult>
		<bndbox>
			<xmin>640</xmin>
			<ymin>469</ymin>
			<xmax>752</xmax>
			<ymax>692</ymax>
		</bndbox>
	</object>
</annotation>
